docs/conf.py
docs/extensions/source.py
examples/fast-plot.py
examples/fw-upgrade.py
examples/hdf5-record.py
examples/hdf5-replay.py
examples/live-plot.py
examples/range-doppler.py
twopilabs/sense/x1000/__init__.py
twopilabs/sense/x1000/scpi_calc.py
twopilabs/sense/x1000/scpi_control.py
twopilabs/sense/x1000/scpi_core.py
twopilabs/sense/x1000/scpi_initiate.py
twopilabs/sense/x1000/scpi_memory.py
twopilabs/sense/x1000/scpi_sense.py
twopilabs/sense/x1000/scpi_system.py
twopilabs/sense/x1000/scpi_trigger.py
twopilabs/sense/x1000/x1000.py
twopilabs/sense/x1000/x1000_base.py
twopilabs/sense/x1000/x1000_scpi.py
twopilabs_sense_x1000-0.7.12.dist-info/licenses/LICENSE
twopilabs_sense_x1000-0.7.12.dist-info/METADATA
twopilabs_sense_x1000-0.7.12.dist-info/WHEEL
twopilabs_sense_x1000-0.7.12.dist-info/top_level.txt
twopilabs_sense_x1000-0.7.12.dist-info/RECORD
